Workbook

Sheet Read Me
B2: Abhiyanta India Solutions — SAP Technical Interview Question Bank (Enhanced)
B3: Arranged by experience bracket | Upload-ready flat master for the evaluation application
B6: How to use
B7: 1. | C7: 'Upload_Master' is the flat sheet for the evaluation application import — one row per question, stable Question_IDs.
B8: 2. | C8: Filter by Module_Code and Experience_Bracket to pull the right set for a candidate's profile.
B9: 3. | C9: Brackets are cumulative for senior candidates: a 7+ yrs candidate should also clear key 3-7 yrs items.
B10: 4. | C10: 'Module_Index' shows question counts per module per bracket (formula-driven).
B11: 5. | C11: 'Rating_Scale' holds the dropdown values to import as the app's rating options.
B13: Experience brackets
B14: L1 — 0-3 yrs | C14: Associate / Junior Consultant — fundamentals, cycles, master data, basic processing
B15: L2 — 3-7 yrs | C15: Consultant / Sr Consultant — configuration depth, integration, statutory, period-end
B16: L3 — 7+ yrs | C16: Lead / Architect — S/4HANA innovations, design decisions, advisory, cloud & AI awareness
B18: Rating scale
B19: Good | C19: Strong, hands-on, can work independently
B20: OK | C20: Working knowledge, productive with light guidance
B21: Basic | C21: Conceptual only / theoretical
B22: Has knowledge (not worked) | C22: Understands but no project exposure
B23: Not worked | C23: No exposure
B24: Bad | C24: Gap / unsatisfactory
B26: Source column | C26: 'Original' = topic from the earlier interview sheets | 'New' = appended enhancement (S/4HANA, cloud, AI, advisory)
B28: www.abhiyantatech.com | Internal — Recruitment use only

Sheet Upload_Master
A1: Question_ID | B1: Module_Code | C1: Module_Name | D1: Experience_Bracket | E1: Bracket_Label | F1: Topic_Category | G1: Question_Topic | H1: Source | I1: Rating (leave blank — filled in app)
A2: FI-L1-01 | B2: FI | C2: Financial Accounting | D2: 0-3 yrs | E2: Associate / Junior (0-3 yrs) | F2: Core Postings | G2: Accounting entries — basic postings & sub-ledger logic (AP/AR/GL) | H2: Original
A3: FI-L1-02 | B3: FI | C3: Financial Accounting | D3: 0-3 yrs | E3: Associate / Junior (0-3 yrs) | F3: Org Structure | G3: Chart of Accounts — importance and how it is finalised with the client | H3: Original
A4: FI-L1-03 | B4: FI | C4: Financial Accounting | D4: 0-3 yrs | E4: Associate / Junior (0-3 yrs) | F4: Org Structure | G4: Profit Centres — use for FI org. structure | H4: Original
A5: FI-L1-04 | B5: FI | C5: Financial Accounting | D5: 0-3 yrs | E5: Associate / Junior (0-3 yrs) | F5: Banking | G5: Bank reconciliation — manual process & basic EBS concept | H5: Original
A6: FI-L1-05 | B6: FI | C6: Financial Accounting | D6: 0-3 yrs | E6: Associate / Junior (0-3 yrs) | F6: Statutory | G6: Withholding tax (TDS) — how it works | H6: Original
A7: FI-L1-06 | B7: FI | C7: Financial Accounting | D7: 0-3 yrs | E7: Associate / Junior (0-3 yrs) | F7: Master Data | G7: GL account groups, field status groups & reconciliation accounts | H7: New
A8: FI-L1-07 | B8: FI | C8: Financial Accounting | D8: 0-3 yrs | E8: Associate / Junior (0-3 yrs) | F8: Core Postings | G8: Document types, number ranges & posting keys | H8: New
A9: FI-L2-01 | B9: FI | C9: Financial Accounting | D9: 3-7 yrs | E9: Consultant / Sr Consultant (3-7 yrs) | F9: Integration | G9: MM-FI integration — OBYC: BSX, PRD, GBB / Valuation Class / mvt 261, 101 | H9: Original
A10: FI-L2-02 | B10: FI | C10: Financial Accounting | D10: 3-7 yrs | E10: Consultant / Sr Consultant (3-7 yrs) | F10: Integration | G10: FI-SD integration — VKOA: account assignment groups, accounting key, SD condition type | H10: Original
A11: FI-L2-03 | B11: FI | C11: Financial Accounting | D11: 3-7 yrs | E11: Consultant / Sr Consultant (3-7 yrs) | F11: Statutory | G11: GST — configuration & day-to-day handling | H11: Original
A12: FI-L2-04 | B12: FI | C12: Financial Accounting | D12: 3-7 yrs | E12: Consultant / Sr Consultant (3-7 yrs) | F12: Statutory | G12: Taxes in SAP — tax code, condition record, tax procedure, access sequence (OB40) | H12: Original
A13: FI-L2-05 | B13: FI | C13: Financial Accounting | D13: 3-7 yrs | E13: Consultant / Sr Consultant (3-7 yrs) | F13: Banking | G13: Electronic bank statement (EBS) — formats, posting rules, interpretation algorithms | H13: Original
... A194: BASIS-L3-05 | B194: BASIS | C194: Basis / Technical & ABAP | D194: 7+ yrs | E194: Lead / Architect (7+ yrs) | F194: AI | G194: ABAP AI / Joule for developers & code migration (custom code remediation) awareness | H194: New

Sheet Module_Index
A1: Module_Code | B1: Module_Name | C1: 0-3 yrs | D1: 3-7 yrs | E1: 7+ yrs | F1: Total
A2: FI | B2: Financial Accounting | C2: =COUNTIFS(Upload_Master!$B:$B,$A2,Upload_Master!$D:$D,"0-3 yrs") -> 7 | D2: =COUNTIFS(Upload_Master!$B:$B,$A2,Upload_Master!$D:$D,"3-7 yrs") -> 12 | E2: =COUNTIFS(Upload_Master!$B:$B,$A2,Upload_Master!$D:$D,"7+ yrs") -> 10 | F2: =SUM(C2:E2) -> 29
A3: CO | B3: Controlling | C3: =COUNTIFS(Upload_Master!$B:$B,$A3,Upload_Master!$D:$D,"0-3 yrs") -> 5 | D3: =COUNTIFS(Upload_Master!$B:$B,$A3,Upload_Master!$D:$D,"3-7 yrs") -> 8 | E3: =COUNTIFS(Upload_Master!$B:$B,$A3,Upload_Master!$D:$D,"7+ yrs") -> 7 | F3: =SUM(C3:E3) -> 20
A4: MM | B4: Materials Management | C4: =COUNTIFS(Upload_Master!$B:$B,$A4,Upload_Master!$D:$D,"0-3 yrs") -> 6 | D4: =COUNTIFS(Upload_Master!$B:$B,$A4,Upload_Master!$D:$D,"3-7 yrs") -> 13 | E4: =COUNTIFS(Upload_Master!$B:$B,$A4,Upload_Master!$D:$D,"7+ yrs") -> 4 | F4: =SUM(C4:E4) -> 23
A5: SD | B5: Sales & Distribution | C5: =COUNTIFS(Upload_Master!$B:$B,$A5,Upload_Master!$D:$D,"0-3 yrs") -> 5 | D5: =COUNTIFS(Upload_Master!$B:$B,$A5,Upload_Master!$D:$D,"3-7 yrs") -> 11 | E5: =COUNTIFS(Upload_Master!$B:$B,$A5,Upload_Master!$D:$D,"7+ yrs") -> 5 | F5: =SUM(C5:E5) -> 21
A6: PP | B6: Production Planning | C6: =COUNTIFS(Upload_Master!$B:$B,$A6,Upload_Master!$D:$D,"0-3 yrs") -> 5 | D6: =COUNTIFS(Upload_Master!$B:$B,$A6,Upload_Master!$D:$D,"3-7 yrs") -> 9 | E6: =COUNTIFS(Upload_Master!$B:$B,$A6,Upload_Master!$D:$D,"7+ yrs") -> 5 | F6: =SUM(C6:E6) -> 19
A7: QM | B7: Quality Management | C7: =COUNTIFS(Upload_Master!$B:$B,$A7,Upload_Master!$D:$D,"0-3 yrs") -> 6 | D7: =COUNTIFS(Upload_Master!$B:$B,$A7,Upload_Master!$D:$D,"3-7 yrs") -> 7 | E7: =COUNTIFS(Upload_Master!$B:$B,$A7,Upload_Master!$D:$D,"7+ yrs") -> 5 | F7: =SUM(C7:E7) -> 18
A8: PM | B8: Plant Maintenance / EAM | C8: =COUNTIFS(Upload_Master!$B:$B,$A8,Upload_Master!$D:$D,"0-3 yrs") -> 4 | D8: =COUNTIFS(Upload_Master!$B:$B,$A8,Upload_Master!$D:$D,"3-7 yrs") -> 8 | E8: =COUNTIFS(Upload_Master!$B:$B,$A8,Upload_Master!$D:$D,"7+ yrs") -> 5 | F8: =SUM(C8:E8) -> 17
A9: WM | B9: Warehouse Management (WM/EWM) | C9: =COUNTIFS(Upload_Master!$B:$B,$A9,Upload_Master!$D:$D,"0-3 yrs") -> 4 | D9: =COUNTIFS(Upload_Master!$B:$B,$A9,Upload_Master!$D:$D,"3-7 yrs") -> 6 | E9: =COUNTIFS(Upload_Master!$B:$B,$A9,Upload_Master!$D:$D,"7+ yrs") -> 7 | F9: =SUM(C9:E9) -> 17
A10: HCM | B10: HCM / SuccessFactors | C10: =COUNTIFS(Upload_Master!$B:$B,$A10,Upload_Master!$D:$D,"0-3 yrs") -> 3 | D10: =COUNTIFS(Upload_Master!$B:$B,$A10,Upload_Master!$D:$D,"3-7 yrs") -> 6 | E10: =COUNTIFS(Upload_Master!$B:$B,$A10,Upload_Master!$D:$D,"7+ yrs") -> 5 | F10: =SUM(C10:E10) -> 14
A11: BASIS | B11: Basis / Technical & ABAP | C11: =COUNTIFS(Upload_Master!$B:$B,$A11,Upload_Master!$D:$D,"0-3 yrs") -> 4 | D11: =COUNTIFS(Upload_Master!$B:$B,$A11,Upload_Master!$D:$D,"3-7 yrs") -> 6 | E11: =COUNTIFS(Upload_Master!$B:$B,$A11,Upload_Master!$D:$D,"7+ yrs") -> 5 | F11: =SUM(C11:E11) -> 15
B12: TOTAL | C12: =SUM(C2:C11) -> 49 | D12: =SUM(D2:D11) -> 86 | E12: =SUM(E2:E11) -> 58 | F12: =SUM(F2:F11) -> 193

Sheet Rating_Scale
A1: Rating_Value | B1: Score (1-5) | C1: Meaning
A2: Good | B2: 5 | C2: Strong, hands-on, can work independently
A3: OK | B3: 4 | C3: Working knowledge, productive with light guidance
A4: Basic | B4: 3 | C4: Conceptual only / theoretical
A5: Has knowledge (not worked) | B5: 2 | C5: Understands but no project exposure
A6: Not worked | B6: 1 | C6: No exposure
A7: Bad | B7: 0 | C7: Gap / unsatisfactory
